<?xml version="1.0"?>
<!DOCTYPE form SYSTEM "../../../templates/entities.dtd">

<form>
    <group name="main">
        <title>Содержание</title>
        
        <element name="title" type="string" is-required="true">
            <label>Название</label>
        </element>
    
        <element name="uri" type="folder" is-required="true">
            <label>Локальная папка</label>
            <description>Можно использовать латинские буквы, цифры и&nbsp;знак подчеркивания.</description>
        </element>
    
        <element name="is_published" type="boolean">
            <label>Раздел доступен</label>
            <value>1</value>
        </element>
    
        <element name="users" type="multiple">
            <label>Пользователи, имеющие доступ</label>
        </element>
    
        <element name="description" type="text">
            <label>Описание</label>
        </element>
    </group>
</form>
